{
    "experiments": [
      {
        "difficulty": "existing research",
        "options": [
          {"left": [400, 400], "right": [750, 400]},
          {"left": [0, 800], "right": [400, 400]},
          {"left": [800, 200], "right": [0, 0]},
          {"left": [200, 700], "right": [600, 600]},
          {"left": [300, 600], "right": [700, 500]},
          {"left": [400, 400], "right": [750, 375]}
        ],
        "metrics": [
          "Berk29",
          "Berk26",
          "Berk23",
          "Berk15",
          "Barc8",
          "Barc2"
        ]
      }
    ]
  }
  